LICENSE
README.md
setup.py
apyxl/__init__.py
apyxl/_misc.py
apyxl/_time_series_normalizer.py
apyxl/_wrapper.py
apyxl/_xgb.py
apyxl.egg-info/PKG-INFO
apyxl.egg-info/SOURCES.txt
apyxl.egg-info/dependency_links.txt
apyxl.egg-info/requires.txt
apyxl.egg-info/top_level.txt
tests/test_timeseriesnormalizer.py
tests/test_xgbwrapper.py