Metadata-Version: 2.1
Name: apyxl
Version: 0.1.4
Summary: A Python package for data analysis and model optimization.
Home-page: https://github.com/CyrilJl/apyxl
Author: Cyril Joly
License-File: LICENSE
Requires-Dist: numpy
Requires-Dist: pandas
Requires-Dist: xgboost>=2.0.0
Requires-Dist: scikit-learn
Requires-Dist: shap
Requires-Dist: hyperopt
Requires-Dist: matplotlib
